LICENSE.txt
MANIFEST.in
README.md
setup.py
bin/compute_divergence.py
bin/explode_fasta.py
bin/fasta2idt.py
bin/fasta2lenhist.py
bin/fasta2tiles.py
bin/fasta2uniq.py
bin/fasta_rm_newlines.py
bin/fasta_sort_by_abundance.py
bin/generate_otu_table.py
bin/generic_script.py
bin/idt2fasta.py
bin/make_timeseries_figures.py
bin/qiime_cluster_jobs_LSF.py
bin/quality_hist.py
bin/sff2fastq_trimmed.py
bin/streamgraph_html.py
bin/timeseries2json.py
bin/timeseries2streamgraph.py
ulutil/SeqRecordLite.py
ulutil/__init__.py
ulutil/analyze_oligos.py
ulutil/blast.py
ulutil/blat.py
ulutil/countdata.py
ulutil/daemonize.py
ulutil/degex.py
ulutil/exonerate.py
ulutil/graphtools.py
ulutil/lsf.py
ulutil/mplextensions.py
ulutil/oligoTm.py
ulutil/primers.py
ulutil/pyutils.py
ulutil/qPCR2melting.py
ulutil/qPCR2quantitation.py
ulutil/sanger.py
ulutil/scale.py
ulutil/seqtools.py
ulutil/statstools.py
ulutil/stitch.py
ulutil/streamgraph.py
ulutil/timeseries.py
ulutil/unafold.py
ulutil.egg-info/PKG-INFO
ulutil.egg-info/SOURCES.txt
ulutil.egg-info/dependency_links.txt
ulutil.egg-info/top_level.txt
ulutil.egg-info/zip-safe