Metadata-Version: 1.1
Name: ulutil
Version: 0.1.1
Summary: Python utilities for Church lab work (mostly DNA sequencing)
Home-page: https://github.com/churchlab/ulutil
Author: Uri Laserson
Author-email: uri.laserson@gmail.com
License: Apache License, Version 2.0
Keywords: python sequencing dna lsf sanger streamgraph oligos primers
Platform: UNKNOWN
Classifier: Programming Language :: Python :: 2
Classifier: Programming Language :: Python :: 2.6
Classifier: Programming Language :: Python :: 2.7
